[
    {
        "segmentation": [
            [
                42.0,
                208.5,
                43.0,
                166.5,
                45.0,
                204.5,
                45.5,
                173.0,
                50.5,
                172.0,
                51.0,
                166.5,
                55.5,
                167.0,
                56.0,
                185.5,
                57.5,
                182.0,
                57.5,
                167.0,
                64.5,
                167.0,
                65.0,
                177.5,
                65.5,
                167.0,
                72.5,
                166.0,
                73.0,
                152.5,
                105.0,
                152.5,
                106.0,
                148.5,
                126.0,
                148.5,
                127.0,
                143.5,
                134.5,
                143.0,
                135.0,
                132.5,
                157.0,
                132.5,
                158.0,
                130.5,
                162.0,
                130.5,
                162.5,
                78.0,
                165.5,
                78.0,
                166.0,
                93.5,
                167.0,
                77.5,
                193.5,
                77.0,
                171.0,
                76.5,
                170.5,
                60.0,
                164.0,
                59.5,
                163.0,
                54.5,
                158.5,
                54.0,
                158.0,
                49.5,
                145.0,
                49.5,
                144.0,
                39.5,
                129.0,
                39.5,
                128.0,
                33.5,
                126.0,
                33.5,
                125.0,
                31.5,
                118.0,
                31.5,
                117.0,
                16.5,
                116.5,
                31.0,
                115.0,
                31.5,
                114.0,
                12.5,
                69.0,
                12.5,
                68.0,
                -0.5,
                67.5,
                12.0,
                56.0,
                12.5,
                55.0,
                7.5,
                54.0,
                18.5,
                49.5,
                18.0,
                49.0,
                4.5,
                41.0,
                4.5,
                40.0,
                2.5,
                39.0,
                4.5,
                36.0,
                4.5,
                35.0,
                13.5,
                14.0,
                13.5,
                13.0,
                8.5,
                12.5,
                13.0,
                10.5,
                14.0,
                10.5,
                44.0,
                9.0,
                28.5,
                8.5,
                45.0,
                -0.5,
                46.0,
                -0.5,
                90.0,
                2.5,
                91.0,
                2.5,
                95.0,
                4.5,
                96.0,
                4.5,
                174.0,
                6.0,
                95.5,
                8.5,
                96.0,
                9.0,
                109.5,
                10.5,
                96.0,
                11.5,
                173.0,
                12.0,
                95.5,
                12.5,
                104.0,
                14.5,
                105.0,
                14.5,
                191.0,
                16.5,
                183.0,
                17.0,
                104.5,
                17.5,
                124.0,
                19.5,
                125.0,
                19.5,
                184.0,
                26.5,
                185.0,
                27.0,
                197.5,
                28.0,
                184.5,
                29.0,
                196.5,
                33.5,
                196.0,
                34.0,
                184.5,
                40.5,
                185.0,
                40.5,
                207.0,
                42.0,
                208.5
            ]
        ],
        "iscrowd": 0,
        "image_id": 27636,
        "category_id": 0,
        "id": 0,
        "bbox": [
            -0.5,
            -0.5,
            194.0,
            209.0
        ],
        "area": 21286.0
    },
    {
        "segmentation": [
            [
                196.0,
                228.5,
                196.5,
                176.0,
                198.5,
                176.0,
                199.0,
                196.5,
                199.5,
                176.0,
                202.5,
                176.0,
                204.0,
                221.5,
                205.5,
                211.0,
                205.5,
                187.0,
                208.5,
                187.0,
                209.0,
                191.5,
                209.5,
                187.0,
                212.5,
                187.0,
                213.0,
                213.5,
                213.5,
                194.0,
                215.0,
                204.5,
                215.5,
                187.0,
                217.5,
                187.0,
                218.0,
                222.5,
                218.5,
                209.0,
                220.0,
                212.5,
                221.0,
                208.5,
                224.5,
                208.0,
                224.5,
                188.0,
                231.5,
                186.0,
                231.5,
                169.0,
                241.0,
                168.5,
                242.0,
                178.5,
                243.0,
                168.5,
                253.5,
                168.0,
                254.0,
                135.5,
                255.5,
                139.0,
                254.5,
                119.0,
                242.0,
                118.5,
                240.5,
                117.0,
                240.0,
                110.5,
                239.0,
                118.5,
                238.0,
                111.5,
                231.5,
                111.0,
                231.5,
                100.0,
                219.0,
                98.5,
                218.0,
                89.5,
                217.0,
                98.5,
                207.0,
                98.5,
                205.0,
                95.5,
                204.0,
                98.5,
                189.0,
                98.5,
                188.0,
                116.5,
                187.0,
                114.5,
                186.0,
                116.5,
                177.0,
                116.5,
                176.0,
                107.5,
                175.0,
                116.5,
                163.0,
                116.5,
                162.5,
                135.0,
                157.5,
                136.0,
                157.0,
                145.5,
                150.5,
                146.0,
                166.0,
                146.5,
                167.0,
                154.5,
                183.5,
                155.0,
                185.0,
                182.5,
                185.5,
                155.0,
                188.5,
                154.0,
                189.5,
                147.0,
                190.0,
                185.5,
                190.5,
                161.0,
                192.5,
                147.0,
                192.5,
                175.0,
                195.5,
                176.0,
                196.0,
                228.5
            ],
            []
        ],
        "iscrowd": 0,
        "image_id": 27636,
        "category_id": 0,
        "id": 1,
        "bbox": [
            150.5,
            89.5,
            105.0,
            139.0
        ],
        "area": 6126.0
    }
]