[
    {
        "segmentation": [
            [
                105.0,
                36.5,
                106.0,
                34.5,
                111.5,
                32.0,
                111.5,
                30.0,
                114.5,
                27.0,
                113.5,
                21.0,
                111.5,
                20.0,
                111.5,
                12.0,
                106.5,
                9.0,
                106.0,
                3.5,
                94.0,
                1.5,
                93.0,
                -0.5,
                92.0,
                1.5,
                88.5,
                2.0,
                88.0,
                4.5,
                85.5,
                5.0,
                83.5,
                10.0,
                81.5,
                11.0,
                81.5,
                18.0,
                83.5,
                19.0,
                83.5,
                22.0,
                85.5,
                23.0,
                87.0,
                28.5,
                93.0,
                29.5,
                96.0,
                35.5,
                97.0,
                32.5,
                101.0,
                36.5,
                105.0,
                36.5
            ]
        ],
        "iscrowd": 0,
        "image_id": 16374,
        "category_id": 0,
        "id": 0,
        "bbox": [
            81.5,
            -0.5,
            33.0,
            37.0
        ],
        "area": 806.75
    },
    {
        "segmentation": [
            [
                17.0,
                58.5,
                22.0,
                56.5,
                25.0,
                52.5,
                30.0,
                51.5,
                31.0,
                47.5,
                34.5,
                47.0,
                35.5,
                37.0,
                33.5,
                36.0,
                32.5,
                26.0,
                30.0,
                22.5,
                22.0,
                21.5,
                20.0,
                17.5,
                14.0,
                17.5,
                11.5,
                19.0,
                11.0,
                21.5,
                4.5,
                24.0,
                3.0,
                30.5,
                -0.5,
                31.0,
                -0.5,
                40.0,
                0.5,
                47.0,
                3.5,
                48.0,
                5.5,
                53.0,
                13.0,
                54.5,
                17.0,
                58.5
            ]
        ],
        "iscrowd": 0,
        "image_id": 16374,
        "category_id": 0,
        "id": 1,
        "bbox": [
            -0.5,
            17.5,
            36.0,
            41.0
        ],
        "area": 1047.25
    },
    {
        "segmentation": [
            [
                120.0,
                127.5,
                123.5,
                124.0,
                123.5,
                121.0,
                126.5,
                120.0,
                127.5,
                114.0,
                124.5,
                111.0,
                123.5,
                103.0,
                119.0,
                99.5,
                116.5,
                102.0,
                116.0,
                105.5,
                111.5,
                106.0,
                110.0,
                111.5,
                103.5,
                115.0,
                108.5,
                118.0,
                110.0,
                124.5,
                112.0,
                124.5,
                114.0,
                127.5,
                120.0,
                127.5
            ]
        ],
        "iscrowd": 0,
        "image_id": 16374,
        "category_id": 0,
        "id": 2,
        "bbox": [
            103.5,
            99.5,
            24.0,
            28.0
        ],
        "area": 370.0
    }
]