[
    {
        "segmentation": [
            [
                53.0,
                65.5,
                53.5,
                62.0,
                57.0,
                61.5,
                59.0,
                57.5,
                65.5,
                57.0,
                66.0,
                50.5,
                69.0,
                50.5,
                70.0,
                48.5,
                71.5,
                51.0,
                77.5,
                36.0,
                75.5,
                35.0,
                74.5,
                30.0,
                74.5,
                18.0,
                72.5,
                17.0,
                72.5,
                10.0,
                69.0,
                9.5,
                67.0,
                5.5,
                60.0,
                5.5,
                59.0,
                1.5,
                55.0,
                1.5,
                54.0,
                -0.5,
                53.0,
                1.5,
                45.0,
                1.5,
                44.0,
                3.5,
                40.0,
                3.5,
                39.0,
                5.5,
                33.5,
                6.0,
                32.5,
                11.0,
                28.5,
                12.0,
                28.5,
                20.0,
                27.5,
                24.0,
                24.5,
                25.0,
                24.5,
                31.0,
                23.0,
                33.5,
                20.5,
                34.0,
                20.5,
                39.0,
                24.5,
                40.0,
                24.5,
                44.0,
                27.5,
                45.0,
                28.0,
                50.5,
                32.0,
                50.5,
                33.0,
                52.5,
                37.0,
                52.5,
                38.0,
                54.5,
                40.0,
                54.5,
                41.0,
                59.5,
                42.0,
                54.5,
                42.5,
                60.0,
                45.0,
                62.5,
                47.0,
                60.5,
                48.0,
                64.5,
                48.5,
                61.0,
                50.0,
                63.5,
                51.0,
                60.5,
                53.0,
                65.5
            ]
        ],
        "iscrowd": 0,
        "image_id": 35458,
        "category_id": 0,
        "id": 0,
        "bbox": [
            20.5,
            -0.5,
            57.0,
            66.0
        ],
        "area": 2454.0
    },
    {
        "segmentation": [
            [
                147.0,
                99.5,
                147.5,
                92.0,
                149.5,
                91.0,
                150.0,
                87.5,
                152.5,
                87.0,
                152.5,
                79.0,
                164.5,
                78.0,
                165.5,
                65.0,
                167.5,
                64.0,
                168.0,
                60.5,
                171.5,
                60.0,
                172.5,
                50.0,
                169.5,
                48.0,
                169.5,
                42.0,
                164.5,
                41.0,
                164.5,
                27.0,
                163.0,
                22.5,
                153.0,
                21.5,
                152.5,
                16.0,
                148.0,
                12.5,
                134.0,
                12.5,
                133.0,
                10.5,
                126.0,
                9.5,
                125.0,
                7.5,
                117.0,
                6.5,
                115.5,
                14.0,
                110.5,
                15.0,
                110.5,
                20.0,
                107.5,
                23.0,
                107.5,
                29.0,
                95.5,
                31.0,
                95.5,
                49.0,
                93.5,
                59.0,
                97.5,
                60.0,
                98.5,
                65.0,
                101.5,
                66.0,
                101.5,
                69.0,
                103.5,
                70.0,
                104.0,
                72.5,
                107.5,
                73.0,
                108.5,
                90.0,
                110.0,
                91.5,
                116.0,
                91.5,
                116.5,
                96.0,
                121.0,
                96.5,
                122.0,
                99.5,
                147.0,
                99.5
            ]
        ],
        "iscrowd": 0,
        "image_id": 35458,
        "category_id": 0,
        "id": 1,
        "bbox": [
            93.5,
            6.5,
            79.0,
            93.0
        ],
        "area": 5065.0
    },
    {
        "segmentation": [
            [
                107.0,
                236.5,
                108.0,
                232.5,
                115.0,
                232.5,
                115.5,
                227.0,
                118.0,
                226.5,
                119.0,
                223.5,
                121.0,
                223.5,
                124.5,
                220.0,
                124.5,
                197.0,
                114.0,
                194.5,
                113.0,
                190.5,
                99.0,
                190.5,
                98.0,
                188.5,
                96.5,
                189.0,
                96.0,
                186.5,
                93.0,
                185.5,
                91.5,
                195.0,
                84.5,
                196.0,
                84.5,
                204.0,
                82.5,
                211.0,
                85.5,
                214.0,
                85.5,
                220.0,
                89.5,
                221.0,
                90.5,
                230.0,
                93.0,
                232.5,
                100.0,
                232.5,
                102.0,
                236.5,
                107.0,
                236.5
            ]
        ],
        "iscrowd": 0,
        "image_id": 35458,
        "category_id": 0,
        "id": 2,
        "bbox": [
            82.5,
            185.5,
            42.0,
            51.0
        ],
        "area": 1485.75
    },
    {
        "segmentation": [
            [
                31.0,
                255.5,
                35.5,
                253.0,
                36.0,
                250.5,
                38.5,
                250.0,
                39.0,
                247.5,
                51.0,
                247.5,
                52.5,
                246.0,
                52.5,
                241.0,
                55.0,
                239.5,
                64.0,
                239.5,
                66.5,
                230.0,
                69.5,
                229.0,
                69.5,
                223.0,
                64.5,
                217.0,
                64.5,
                212.0,
                61.5,
                211.0,
                61.5,
                208.0,
                60.0,
                206.5,
                52.0,
                206.5,
                50.5,
                201.0,
                48.0,
                198.5,
                44.0,
                195.5,
                43.0,
                197.5,
                41.0,
                197.5,
                40.0,
                194.5,
                39.0,
                196.5,
                19.0,
                197.5,
                16.5,
                204.0,
                11.0,
                204.5,
                10.0,
                209.5,
                3.0,
                211.5,
                2.5,
                218.0,
                -0.5,
                219.0,
                -0.5,
                235.0,
                2.5,
                236.0,
                4.0,
                239.5,
                6.5,
                240.0,
                6.5,
                244.0,
                10.5,
                245.0,
                10.5,
                247.0,
                13.5,
                249.0,
                14.0,
                252.5,
                28.0,
                253.5,
                31.0,
                255.5
            ]
        ],
        "iscrowd": 0,
        "image_id": 35458,
        "category_id": 0,
        "id": 3,
        "bbox": [
            -0.5,
            194.5,
            70.0,
            61.0
        ],
        "area": 2925.0
    }
]